django_sftp/__init__.py
django_sftp/admin.py
django_sftp/apps.py
django_sftp/compat.py
django_sftp/filesystem.py
django_sftp/interface.py
django_sftp/management/__init__.py
django_sftp/management/commands/__init__.py
django_sftp/management/commands/createsftpuseraccount.py
django_sftp/management/commands/createsftpusergroup.py
django_sftp/management/commands/sftpserver.py
django_sftp/migrations/0001_initial.py
django_sftp/migrations/__init__.py
django_sftp/mixins.py
django_sftp/models.py
django_sftp/py.typed
django_sftp-0.2.2.dist-info/entry_points.txt
django_sftp-0.2.2.dist-info/LICENSE
django_sftp-0.2.2.dist-info/WHEEL
django_sftp-0.2.2.dist-info/METADATA
django_sftp-0.2.2.dist-info/RECORD
