Metadata-Version: 2.1
Name: django-sftp
Version: 0.2.2
Summary: Django SFTP
Home-page: https://github.com/vahaah/django-sftp
License: MIT
Author: Alex Vakhitov
Author-email: alex@vakhitov.dev
Requires-Python: >=3.7,<4.0.0
Classifier: Development Status :: 3 - Alpha
Classifier: Framework :: Django :: 2.1
Classifier: Framework :: Django :: 2.2
Classifier: Framework :: Django :: 3.0
Classifier: Framework :: Django :: 3.1
Classifier: License :: OSI Approved :: MIT License
Classifier: Programming Language :: Python :: 3
Classifier: Programming Language :: Python :: 3.7
Classifier: Programming Language :: Python :: 3.8
Classifier: Programming Language :: Python :: 3.9
Requires-Dist: asyncssh (>=2.4.2,<3.0.0)
Requires-Dist: click (>=7.0,<8.0)
Project-URL: Changelog, https://github.com/vahaah/django-sftp/releases
Project-URL: Documentation, https://django-sftp.readthedocs.io
Project-URL: Repository, https://github.com/vahaah/django-sftp
